<?xml version = '1.0' encoding = 'UTF-8'?>
<Relation class="oracle.dbtools.crest.model.design.logical.Relation" name="Relation_11" directorySegmentName="seg_0" id="E53226AC-F81D-8963-DF7B-013205DB4C1B">
<createdBy>Rukin</createdBy>
<createdTime>2024-05-13 14:47:08 UTC</createdTime>
<ownerDesignName>data_scheme</ownerDesignName>
<engineerTo>
<item key="4B704B68-836D-50B1-3F67-1330F6B88EA8" value="true"/>
</engineerTo>
<sourcePk>0169374D-E7CB-1FB2-D73B-60D0CFDF0DA5</sourcePk>
<identifying>false</identifying>
<optionalSource>true</optionalSource>
<optionalTarget>false</optionalTarget>
<sourceCardinality>1</sourceCardinality>
<sourceEntity>B161EC19-94E7-88EC-D3AD-045A5FABCF71</sourceEntity>
<targetCardinalityString>*</targetCardinalityString>
<targetEntity>59218C04-6FFD-5FFC-97EB-39F8761B4FF9</targetEntity>
<transferable>true</transferable>
<deleteRule>CASCADE</deleteRule>
</Relation>